sodasql/dataset_analyzer.py
sodasql/version.py
sodasql/cli/cli.py
sodasql/cli/indenting_yaml_dumper.py
sodasql/common/json_helper.py
sodasql/common/logging_helper.py
sodasql/common/yaml_helper.py
sodasql/dialects/athena_dialect.py
sodasql/dialects/bigquery_dialect.py
sodasql/dialects/hive_dialect.py
sodasql/dialects/postgres_dialect.py
sodasql/dialects/redshift_dialect.py
sodasql/dialects/snowflake_dialect.py
sodasql/dialects/sqlserver_dialect.py
sodasql/exceptions/exceptions.py
sodasql/scan/aws_credentials.py
sodasql/scan/column_metadata.py
sodasql/scan/db.py
sodasql/scan/dialect.py
sodasql/scan/dialect_parser.py
sodasql/scan/env_vars.py
sodasql/scan/file_system.py
sodasql/scan/group_value.py
sodasql/scan/measurement.py
sodasql/scan/metric.py
sodasql/scan/missing.py
sodasql/scan/parser.py
sodasql/scan/sampler.py
sodasql/scan/samples_yml.py
sodasql/scan/scan.py
sodasql/scan/scan_builder.py
sodasql/scan/scan_column.py
sodasql/scan/scan_error.py
sodasql/scan/scan_result.py
sodasql/scan/scan_yml.py
sodasql/scan/scan_yml_column.py
sodasql/scan/scan_yml_parser.py
sodasql/scan/sql_metric_yml.py
sodasql/scan/test.py
sodasql/scan/test_result.py
sodasql/scan/warehouse.py
sodasql/scan/warehouse_yml.py
sodasql/scan/warehouse_yml_parser.py
sodasql/scan/validity/__init__.py
sodasql/scan/validity/money_patterns.py
sodasql/soda_server_client/soda_server_client.py
soda_sql-2.0.0b27.dist-info/LICENSE
soda_sql-2.0.0b27.dist-info/METADATA
soda_sql-2.0.0b27.dist-info/WHEEL
soda_sql-2.0.0b27.dist-info/entry_points.txt
soda_sql-2.0.0b27.dist-info/top_level.txt
soda_sql-2.0.0b27.dist-info/RECORD
