Metadata-Version: 2.1
Name: soda-sql
Version: 2.0.0b27
Summary: Soda SQL library & CLI
Home-page: UNKNOWN
Author: Tom Baeyens
Author-email: tom@soda.io
License: UNKNOWN
Platform: UNKNOWN
Requires-Dist: asn1crypto (==1.4.0)
Requires-Dist: azure-common (==1.1.25)
Requires-Dist: azure-core (==1.8.2)
Requires-Dist: azure-storage-blob (==12.5.0)
Requires-Dist: boto3 (==1.15.18)
Requires-Dist: botocore (==1.18.18)
Requires-Dist: cachetools (==4.2.0)
Requires-Dist: certifi (==2020.12.5)
Requires-Dist: cffi (==1.14.3)
Requires-Dist: chardet (==3.0.4)
Requires-Dist: click (==7.1.2)
Requires-Dist: cryptography (==3.3.2)
Requires-Dist: future (==0.18.2)
Requires-Dist: google-api-core[grpc] (==1.24.1)
Requires-Dist: google-auth (==1.24.0)
Requires-Dist: google-cloud-bigquery (==2.5.0)
Requires-Dist: google-cloud-core (==1.5.0)
Requires-Dist: google-crc32c (==1.1.0)
Requires-Dist: google-resumable-media (==1.2.0)
Requires-Dist: googleapis-common-protos (==1.52.0)
Requires-Dist: grpcio (==1.34.0)
Requires-Dist: idna (==2.10)
Requires-Dist: isodate (==0.6.0)
Requires-Dist: jinja2 (==2.11.3)
Requires-Dist: jmespath (==0.10.0)
Requires-Dist: markupsafe (==1.1.1)
Requires-Dist: msrest (==0.6.19)
Requires-Dist: oauthlib (==3.1.0)
Requires-Dist: oscrypto (==1.2.1)
Requires-Dist: proto-plus (==1.13.0)
Requires-Dist: protobuf (==3.14.0)
Requires-Dist: psycopg2-binary (==2.8.5)
Requires-Dist: pyasn1-modules (==0.2.8)
Requires-Dist: pyasn1 (==0.4.8)
Requires-Dist: pyathena (==2.2.0)
Requires-Dist: pycparser (==2.20)
Requires-Dist: pycryptodomex (==3.9.8)
Requires-Dist: pyhive (==0.6.3)
Requires-Dist: pyjwt (==1.7.1)
Requires-Dist: pyodbc (==4.0.30)
Requires-Dist: pyopenssl (==19.1.0)
Requires-Dist: python-dateutil (==2.8.1)
Requires-Dist: pytz (==2020.1)
Requires-Dist: pyyaml (==5.4.1)
Requires-Dist: requests-oauthlib (==1.3.0)
Requires-Dist: requests (==2.23.0)
Requires-Dist: rsa (==4.6)
Requires-Dist: s3transfer (==0.3.3)
Requires-Dist: six (==1.15.0)
Requires-Dist: snowflake-connector-python (==2.4.0)
Requires-Dist: tenacity (==6.2.0)
Requires-Dist: thrift (==0.13.0)
Requires-Dist: urllib3 (==1.25.10)
